setup.cfg
setup.py
ev3/__init__.py
ev3/ev3dev.py
ev3/event_loop.py
ev3/lego.py
ev3/mindsensors.py
python_ev3.egg-info/PKG-INFO
python_ev3.egg-info/SOURCES.txt
python_ev3.egg-info/dependency_links.txt
python_ev3.egg-info/top_level.txt
test/test_ev3_battery_percentage.py
test/test_ev3_i2cs.py
test/test_ev3_key.py
test/test_ev3_lcd.py
test/test_ev3_led.py
test/test_ev3_legosensor.py
test/test_ev3_motor.py
test/test_ev3_tone.py
test/test_lego_color_sensor.py
test/test_lego_gyro_sensor.py
test/test_lego_infrared_sensor_sensor.py
test/test_lego_large_motor.py
test/test_lego_medium_motor.py
test/test_lego_touch_sensor.py
test/test_lego_ultrasonic_sensor.py
test/test_mindsensors_absolute_IMU.py
test/test_mindsensors_pspnxv4.py