Metadata-Version: 1.1
Name: python-ev3
Version: 0.0.2.8
Summary: Python library of ev3dev firmware
Home-page: https://github.com/topikachu/python-ev3
Author: Gong Yi
Author-email: topikachu@163.com
License: Apache License 2.0
Download-URL: https://github.com/topikachu/python-ev3/releases/tag/0.0.2.8
Platform: UNKNOWN
